setup.py
daliuge_runtime.egg-info/PKG-INFO
daliuge_runtime.egg-info/SOURCES.txt
daliuge_runtime.egg-info/dependency_links.txt
daliuge_runtime.egg-info/entry_points.txt
daliuge_runtime.egg-info/requires.txt
daliuge_runtime.egg-info/top_level.txt
dlg/__init__.py
dlg/dask_emulation.py
dlg/ddap_protocol.py
dlg/drop.py
dlg/droputils.py
dlg/event.py
dlg/graph_loader.py
dlg/io.py
dlg/json_drop.py
dlg/meta.py
dlg/ngaslite.py
dlg/remote.py
dlg/restserver.py
dlg/rpc.py
dlg/s3_drop.py
dlg/shoreClient.py
dlg/testutils.py
dlg/utils.py
dlg/apps/__init__.py
dlg/apps/archiving.py
dlg/apps/bash_shell_app.py
dlg/apps/crc.py
dlg/apps/dlg_app.h
dlg/apps/dlg_app2.h
dlg/apps/dockerapp.py
dlg/apps/dynlib.py
dlg/apps/fileimport.py
dlg/apps/mpi.py
dlg/apps/pyfunc.py
dlg/apps/scp.py
dlg/apps/simple.py
dlg/apps/socket_listener.py
dlg/apps/spead_receiver.py
dlg/deploy/__init__.py
dlg/deploy/common.py
dlg/deploy/pawsey/__init__.py
dlg/deploy/pawsey/dfms_monitor.py
dlg/deploy/pawsey/dfms_proxy.py
dlg/deploy/pawsey/remotes.py
dlg/deploy/pawsey/scale_test.py
dlg/deploy/pawsey/slurm_utils.py
dlg/deploy/pawsey/start_dfms_cluster.py
dlg/lifecycle/__init__.py
dlg/lifecycle/dlm.py
dlg/lifecycle/registry.py
dlg/lifecycle/hsm/__init__.py
dlg/lifecycle/hsm/manager.py
dlg/lifecycle/hsm/store.py
dlg/manager/__init__.py
dlg/manager/client.py
dlg/manager/cmdline.py
dlg/manager/composite_manager.py
dlg/manager/constants.py
dlg/manager/drop_manager.py
dlg/manager/node_manager.py
dlg/manager/proc_daemon.py
dlg/manager/replay.py
dlg/manager/rest.py
dlg/manager/session.py
dlg/manager/web/dim.html
dlg/manager/web/dm.html
dlg/manager/web/session.html
dlg/manager/web/static/css/bootstrap.min.css
dlg/manager/web/static/css/session.css
dlg/manager/web/static/fonts/glyphicons-halflings-regular.eot
dlg/manager/web/static/fonts/glyphicons-halflings-regular.svg
dlg/manager/web/static/fonts/glyphicons-halflings-regular.ttf
dlg/manager/web/static/fonts/glyphicons-halflings-regular.woff
dlg/manager/web/static/fonts/glyphicons-halflings-regular.woff2
dlg/manager/web/static/js/bootbox.min.js
dlg/manager/web/static/js/bootstrap.min.js
dlg/manager/web/static/js/dm.js
dlg/manager/web/static/js/jquery-1.11.3.min.js
dlg/manager/web/static/js/d3/d3.v3.min.js
